odoo/addons/privacy_consent/README.rst
odoo/addons/privacy_consent/__init__.py
odoo/addons/privacy_consent/__manifest__.py
odoo/addons/privacy_consent/controllers/__init__.py
odoo/addons/privacy_consent/controllers/main.py
odoo/addons/privacy_consent/data/ir_actions_server.xml
odoo/addons/privacy_consent/data/ir_cron.xml
odoo/addons/privacy_consent/data/mail.xml
odoo/addons/privacy_consent/i18n/de.po
odoo/addons/privacy_consent/i18n/es.po
odoo/addons/privacy_consent/i18n/fr.po
odoo/addons/privacy_consent/i18n/privacy_consent.pot
odoo/addons/privacy_consent/i18n/pt.po
odoo/addons/privacy_consent/models/__init__.py
odoo/addons/privacy_consent/models/mail_mail.py
odoo/addons/privacy_consent/models/mail_template.py
odoo/addons/privacy_consent/models/privacy_activity.py
odoo/addons/privacy_consent/models/privacy_consent.py
odoo/addons/privacy_consent/models/res_partner.py
odoo/addons/privacy_consent/readme/CONTRIBUTORS.rst
odoo/addons/privacy_consent/readme/DESCRIPTION.rst
odoo/addons/privacy_consent/readme/INSTALL.rst
odoo/addons/privacy_consent/readme/USAGE.rst
odoo/addons/privacy_consent/security/ir.model.access.csv
odoo/addons/privacy_consent/static/description/icon.png
odoo/addons/privacy_consent/static/description/index.html
odoo/addons/privacy_consent/static/src/css/privacy_consent.scss
odoo/addons/privacy_consent/templates/assets.xml
odoo/addons/privacy_consent/templates/form.xml
odoo/addons/privacy_consent/tests/__init__.py
odoo/addons/privacy_consent/tests/test_consent.py
odoo/addons/privacy_consent/views/privacy_activity.xml
odoo/addons/privacy_consent/views/privacy_consent.xml
odoo/addons/privacy_consent/views/res_partner.xml
odoo13_addon_privacy_consent-13.0.1.0.4.dist-info/METADATA
odoo13_addon_privacy_consent-13.0.1.0.4.dist-info/WHEEL
odoo13_addon_privacy_consent-13.0.1.0.4.dist-info/top_level.txt
odoo13_addon_privacy_consent-13.0.1.0.4.dist-info/RECORD
